thermal_comfort/__init__.py
thermal_comfort/_thermal_comfort.cpython-311-x86_64-linux-gnu.so
thermal_comfort/models.py
thermal_comfort/py.typed
thermal_comfort/utils.py
thermal_comfort/_thermal_comfort/__init__.pyi
thermal_comfort/_thermal_comfort/thermal_comfort_mod.pyi
thermal_comfort_omp.libs/libgfortran-8f1e9814.so.5.0.0
thermal_comfort_omp.libs/libgomp-870cb1d0.so.1.0.0
thermal_comfort_omp.libs/libmvec-2-06864e43.28.so
thermal_comfort_omp.libs/libquadmath-828275a7.so.0.0.0
thermal_comfort_omp-1.1.5.dist-info/METADATA
thermal_comfort_omp-1.1.5.dist-info/WHEEL
thermal_comfort_omp-1.1.5.dist-info/RECORD
thermal_comfort_omp-1.1.5.dist-info/licenses/LICENSE
thermal_comfort_omp-1.1.5.dist-info/licenses/LICENSE_pet
thermal_comfort_omp-1.1.5.dist-info/licenses/LICENSE_pythermalcomfort
thermal_comfort_omp-1.1.5.dist-info/licenses/LICENSE_utci
