Metadata-Version: 2.4
Name: thermal-comfort-omp
Version: 1.1.5
Summary: Functions to calculate thermal comfort indices
Author: Jonas Kittner
Maintainer-Email: Jonas Kittner <jonas.kittner@rub.de>
License-File: LICENSE
License-File: LICENSE_pet
License-File: LICENSE_pythermalcomfort
License-File: LICENSE_utci
Classifier: Programming Language :: Python :: 3
Classifier: Programming Language :: Python :: 3 :: Only
Classifier: Programming Language :: Python :: Implementation :: CPython
Project-URL: Repository, https://github.com/RUBclim/thermal-comfort
Project-URL: Issues, https://github.com/RUBclim/thermal-comfort/issues
Requires-Python: >=3.9
Requires-Dist: numpy>=2.0.0
